src/__init__.py
src/kuramoto_model.py
kuramoto_model-0.0.1.dist-info/METADATA
kuramoto_model-0.0.1.dist-info/WHEEL
kuramoto_model-0.0.1.dist-info/license_files/LICENSE
kuramoto_model-0.0.1.dist-info/RECORD
