Metadata-Version: 2.1
Name: kuramoto-model
Version: 0.0.1
Summary: A python implementation of the Kuramoto model
Project-URL: Homepage, https://github.com/rishabhBapat/Kuramoto-Model
Project-URL: Bug Tracker, https://github.com/rishabhBapat/Kuramoto-Model/issues
Author-email: Rishabh Bapat <rishabhbapat@gmail.com>
License: Copyright (c) 2022 Rishabh Bapat
Classifier: License :: OSI Approved :: MIT License
Classifier: Operating System :: OS Independent
Classifier: Programming Language :: Python :: 3
Requires-Python: >=3.7
